audioarxiv/__init__.py
audioarxiv/audio/__init__.py
audioarxiv/audio/base.py
audioarxiv/preprocess/__init__.py
audioarxiv/preprocess/article.py
audioarxiv/preprocess/math_equation.py
audioarxiv/resources/__init__.py
audioarxiv/resources/paper.py
audioarxiv/tools/__init__.py
audioarxiv/tools/main.py
audioarxiv-0.1.2.dist-info/entry_points.txt
audioarxiv-0.1.2.dist-info/licenses/LICENSE
audioarxiv-0.1.2.dist-info/WHEEL
audioarxiv-0.1.2.dist-info/METADATA
audioarxiv-0.1.2.dist-info/RECORD
