Metadata-Version: 2.4
Name: audioarxiv
Version: 0.1.2
Summary: Turn arXiv papers into audio. audioarxiv lets you fetch the research papers from arXiv and read them aloud.
Author-email: "Isaac C. F. Wong" <isaac.cf.wong@gmail.com>
Requires-Python: >=3.9
Classifier: Development Status :: 3 - Alpha
Classifier: Intended Audience :: Science/Research
Classifier: License :: OSI Approved :: MIT License
Classifier: Programming Language :: Python :: 3 :: Only
Classifier: Programming Language :: Python :: 3.9
Classifier: Programming Language :: Python :: 3.10
Classifier: Programming Language :: Python :: 3.11
Classifier: Programming Language :: Python :: 3.12
License-File: LICENSE
Requires-Dist: configargparse
Requires-Dist: arxiv
Requires-Dist: pyttsx3
Requires-Dist: pymupdf
Requires-Dist: sympy
Requires-Dist: nltk
Requires-Dist: pandas
Requires-Dist: platformdirs
Requires-Dist: pytest ; extra == "dev"
Requires-Dist: pre-commit ; extra == "dev"
Requires-Dist: black ; extra == "dev"
Requires-Dist: flake8 ; extra == "dev"
Requires-Dist: pyspark>=3.0.0 ; extra == "spark"
Requires-Dist: bandit[toml]==1.8.3 ; extra == "test"
Requires-Dist: black==25.1.0 ; extra == "test"
Requires-Dist: check-manifest==0.50 ; extra == "test"
Requires-Dist: flake8-bugbear==24.12.12 ; extra == "test"
Requires-Dist: flake8-docstrings ; extra == "test"
Requires-Dist: flake8-formatter_junit_xml ; extra == "test"
Requires-Dist: flake8 ; extra == "test"
Requires-Dist: flake8-pyproject ; extra == "test"
Requires-Dist: pre-commit==4.2.0 ; extra == "test"
Requires-Dist: pylint==3.3.6 ; extra == "test"
Requires-Dist: pylint_junit ; extra == "test"
Requires-Dist: pytest-cov==6.1.1 ; extra == "test"
Requires-Dist: pytest-mock<3.14.1 ; extra == "test"
Requires-Dist: pytest-runner ; extra == "test"
Requires-Dist: pytest==8.3.5 ; extra == "test"
Requires-Dist: pytest-github-actions-annotate-failures ; extra == "test"
Requires-Dist: shellcheck-py==0.10.0.1 ; extra == "test"
Project-URL: Documentation, https://isaac-cf-wong.github.io/audioarxiv
Project-URL: Homepage, https://github.com/isaac-cf-wong/audioarxiv
Project-URL: Release Notes, https://github.com/isaac-cf-wong/audioarxiv/releases
Project-URL: Source, https://github.com/isaac-cf-wong/audioarxiv
Project-URL: Tracker, https://github.com/isaac-cf-wong/audioarxiv/issues
Provides-Extra: dev
Provides-Extra: spark
Provides-Extra: test
